timedfunc.py
timedfunc-1.1.2.dist-info/LICENSE
timedfunc-1.1.2.dist-info/WHEEL
timedfunc-1.1.2.dist-info/METADATA
timedfunc-1.1.2.dist-info/RECORD
