Metadata-Version: 2.1
Name: timedfunc
Version: 1.1.2
Summary: Measures execution time of Python functions using decorators.
Home-page: https://github.com/dapaulid/timedfunc
Author: Daniel Pauli
Author-email: dapaulid@gmail.com
Classifier: License :: OSI Approved :: MIT License
